minkarr/__init__.py
minkarr/globs.py
minkarr/karr.py
minkarr/utils.py
minkarr/data_preprocess/gen_obj_alias_clean_dict.py
minkarr/data_preprocess/wikidata_get.py
minkarr-0.1.7.dist-info/METADATA
minkarr-0.1.7.dist-info/WHEEL
minkarr-0.1.7.dist-info/RECORD
