Metadata-Version: 2.4
Name: minkarr
Version: 0.1.7
Summary: A minimal implementation of KaRR knowledge assessment method for Large Language Models (LLMs)
Author-email: Hichem Ammar Khodja <hichem.ammarkhodja@orange.com>
Requires-Python: >=3.8
Requires-Dist: jsonlines>=4.0.0
Requires-Dist: nltk>=3.9.1
Requires-Dist: setuptools>=70.0.0
Requires-Dist: transformers>=4.46.0
Requires-Dist: wikidataintegrator>=0.9.30
